[
  {
    "waktu": "10 Jan 2026 21:58:25 WIB",
    "lintang": "3.64 LU",
    "bujur": "126.98 BT",
    "magnitudo": "7.1",
    "kedalaman": "17 km",
    "dirasakan": "III-IV Tobelo, III-IV Sitaro, II-III Ternate, II-III Minahasa Utara, II-III Bitung, III Morotai, IV-V Talaud, II-III Manado"
  },
  {
    "waktu": "10 Jan 2026 16:34:07 WIB",
    "lintang": "9.26 LS",
    "bujur": "114.78 BT",
    "magnitudo": "4.5",
    "kedalaman": "34 km",
    "dirasakan": "II-III Kuta, II Jembrana, III Kuta Selatan, II-III Denpasar"
  },
  {
    "waktu": "09 Jan 2026 22:08:07 WIB",
    "lintang": "0.72 LS",
    "bujur": "127.54 BT",
    "magnitudo": "3.2",
    "kedalaman": "4 km",
    "dirasakan": "II-III Labuha"
  },
  {
    "waktu": "09 Jan 2026 21:43:56 WIB",
    "lintang": "0.72 LS",
    "bujur": "127.49 BT",
    "magnitudo": "2.3",
    "kedalaman": "1 km",
    "dirasakan": "II Labuha"
  },
  {
    "waktu": "09 Jan 2026 21:23:55 WIB",
    "lintang": "0.68 LS",
    "bujur": "127.53 BT",
    "magnitudo": "3.5",
    "kedalaman": "4 km",
    "dirasakan": "III Labuha"
  },
  {
    "waktu": "09 Jan 2026 08:35:23 WIB",
    "lintang": "5.62 LS",
    "bujur": "103.72 BT",
    "magnitudo": "4.5",
    "kedalaman": "23 km",
    "dirasakan": "III Bengkunat, II Sekincau, II Liwa, II Suoh"
  },
  {
    "waktu": "09 Jan 2026 01:54:34 WIB",
    "lintang": "4.74 LU",
    "bujur": "96.77 BT",
    "magnitudo": "2.6",
    "kedalaman": "6 km",
    "dirasakan": "II Bener Meriah"
  },
  {
    "waktu": "08 Jan 2026 21:57:14 WIB",
    "lintang": "0.60 LS",
    "bujur": "127.63 BT",
    "magnitudo": "4.3",
    "kedalaman": "3 km",
    "dirasakan": "III Labuha"
  },
  {
    "waktu": "07 Jan 2026 22:58:40 WIB",
    "lintang": "0.21 LS",
    "bujur": "119.82 BT",
    "magnitudo": "3.4",
    "kedalaman": "4 km",
    "dirasakan": "II - III Sirenja"
  },
  {
    "waktu": "07 Jan 2026 17:28:36 WIB",
    "lintang": "8.23 LS",
    "bujur": "116.58 BT",
    "magnitudo": "3.7",
    "kedalaman": "10 km",
    "dirasakan": "III Lombok Timur"
  },
  {
    "waktu": "06 Jan 2026 07:11:32 WIB",
    "lintang": "0.61 LS",
    "bujur": "119.84 BT",
    "magnitudo": "3.5",
    "kedalaman": "10 km",
    "dirasakan": "II-III Palu Utara"
  },
  {
    "waktu": "06 Jan 2026 03:27:48 WIB",
    "lintang": "3.66 LS",
    "bujur": "128.17 BT",
    "magnitudo": "1.7",
    "kedalaman": "10 km",
    "dirasakan": "I-II Ambon"
  },
  {
    "waktu": "05 Jan 2026 22:59:45 WIB",
    "lintang": "3.66 LS",
    "bujur": "128.16 BT",
    "magnitudo": "2.6",
    "kedalaman": "6 km",
    "dirasakan": "II Ambon"
  },
  {
    "waktu": "04 Jan 2026 03:54:48 WIB",
    "lintang": "4.75 LU",
    "bujur": "96.81 BT",
    "magnitudo": "2.8",
    "kedalaman": "6 km",
    "dirasakan": "III-IV Bener Meriah, III-IV Aceh Tengah"
  },
  {
    "waktu": "04 Jan 2026 03:00:36 WIB",
    "lintang": "3.30 LS",
    "bujur": "105.53 BT",
    "magnitudo": "4.4",
    "kedalaman": "17 km",
    "dirasakan": "II-III Sukarami"
  }
]