[
  {
    "waktu": "28 Feb 2026 04:49:14 WIB",
    "lintang": "3.76 LS",
    "bujur": "133.52 BT",
    "magnitudo": "3.8",
    "kedalaman": "31 km",
    "dirasakan": "III Kaimana"
  },
  {
    "waktu": "28 Feb 2026 02:21:28 WIB",
    "lintang": "7.79 LS",
    "bujur": "117.35 BT",
    "magnitudo": "4.7",
    "kedalaman": "18 km",
    "dirasakan": "II Sumbawa Barat, II Sumbawa, II Bima, II Lombok Timur"
  },
  {
    "waktu": "27 Feb 2026 13:06:06 WIB",
    "lintang": "1.47 LU",
    "bujur": "118.81 BT",
    "magnitudo": "4.3",
    "kedalaman": "10 km",
    "dirasakan": "III Maratua, II Karangan"
  },
  {
    "waktu": "25 Feb 2026 10:18:54 WIB",
    "lintang": "4.79 LU",
    "bujur": "95.60 BT",
    "magnitudo": "4.2",
    "kedalaman": "53 km",
    "dirasakan": "II-III Lamno Aceh Jaya"
  },
  {
    "waktu": "24 Feb 2026 22:20:46 WIB",
    "lintang": "4.60 LU",
    "bujur": "96.94 BT",
    "magnitudo": "2.8",
    "kedalaman": "5 km",
    "dirasakan": "II Bener Meriah"
  },
  {
    "waktu": "24 Feb 2026 14:46:50 WIB",
    "lintang": "1.96 LS",
    "bujur": "138.95 BT",
    "magnitudo": "5.7",
    "kedalaman": "10 km",
    "dirasakan": "II-III Kota Jayapura, V Sarmi"
  },
  {
    "waktu": "24 Feb 2026 10:08:39 WIB",
    "lintang": "6.73 LS",
    "bujur": "106.54 BT",
    "magnitudo": "3.1",
    "kedalaman": "16 km",
    "dirasakan": "III Kalapanunggal, III Kabandungan, II-III Leuwiliang"
  },
  {
    "waktu": "23 Feb 2026 20:48:34 WIB",
    "lintang": "4.73 LU",
    "bujur": "96.79 BT",
    "magnitudo": "2.2",
    "kedalaman": "12 km",
    "dirasakan": "II-III Bener Meriah"
  },
  {
    "waktu": "23 Feb 2026 18:36:05 WIB",
    "lintang": "9.26 LS",
    "bujur": "115.65 BT",
    "magnitudo": "4.0",
    "kedalaman": "44 km",
    "dirasakan": "II Kuta, II Kuta Selatan, II Klungkung, II Lombok Barat, II Lombok Tengah"
  },
  {
    "waktu": "23 Feb 2026 06:39:26 WIB",
    "lintang": "5.42 LS",
    "bujur": "122.92 BT",
    "magnitudo": "2.7",
    "kedalaman": "5 km",
    "dirasakan": "II-III Pasarwajo"
  },
  {
    "waktu": "23 Feb 2026 05:59:17 WIB",
    "lintang": "6.70 LS",
    "bujur": "107.34 BT",
    "magnitudo": "2.6",
    "kedalaman": "12 km",
    "dirasakan": "II Cirata, II Cipendeuy"
  },
  {
    "waktu": "22 Feb 2026 23:57:46 WIB",
    "lintang": "6.94 LU",
    "bujur": "116.26 BT",
    "magnitudo": "7.2",
    "kedalaman": "628 km",
    "dirasakan": "II Tanjung Selor, II Malinau, II Tarakan, II Tenggarong, II Samarinda"
  },
  {
    "waktu": "22 Feb 2026 22:55:07 WIB",
    "lintang": "2.89 LS",
    "bujur": "101.07 BT",
    "magnitudo": "3.9",
    "kedalaman": "27 km",
    "dirasakan": "II Mukomuko"
  },
  {
    "waktu": "22 Feb 2026 22:35:41 WIB",
    "lintang": "0.74 LS",
    "bujur": "99.14 BT",
    "magnitudo": "5.2",
    "kedalaman": "29 km",
    "dirasakan": "III Kepulauan Mentawai, III Pasaman Barat, III Agam, II Pariaman, II Padang, II Padang Pariaman, II Padang Panjang, II Bukittinggi"
  },
  {
    "waktu": "22 Feb 2026 04:05:10 WIB",
    "lintang": "4.26 LU",
    "bujur": "97.56 BT",
    "magnitudo": "4.2",
    "kedalaman": "10 km",
    "dirasakan": "II-III Gayo Lues, II Bener Meriah"
  }
]